semantic_kernel_builtsimple/__init__.py
semantic_kernel_builtsimple/client.py
semantic_kernel_builtsimple/plugins.py
semantic_kernel_builtsimple/py.typed
semantic_kernel_builtsimple-0.1.0.dist-info/METADATA
semantic_kernel_builtsimple-0.1.0.dist-info/WHEEL
semantic_kernel_builtsimple-0.1.0.dist-info/licenses/LICENSE
semantic_kernel_builtsimple-0.1.0.dist-info/RECORD
