Metadata-Version: 2.4
Name: semantic-kernel-builtsimple
Version: 0.1.0
Summary: Semantic Kernel plugins for Built-Simple research APIs (PubMed, ArXiv, Wikipedia)
Project-URL: Homepage, https://github.com/built-simple/semantic-kernel-builtsimple
Project-URL: Documentation, https://github.com/built-simple/semantic-kernel-builtsimple#readme
Project-URL: Repository, https://github.com/built-simple/semantic-kernel-builtsimple
Project-URL: Issues, https://github.com/built-simple/semantic-kernel-builtsimple/issues
Author-email: Built-Simple <dev@built-simple.ai>
License-Expression: MIT
License-File: LICENSE
Keywords: ai,arxiv,plugins,pubmed,rag,research,semantic-kernel,wikipedia
Classifier: Development Status :: 4 - Beta
Classifier: Intended Audience :: Developers
Classifier: Intended Audience :: Science/Research
Classifier: License :: OSI Approved :: MIT License
Classifier: Programming Language :: Python :: 3
Classifier: Programming Language :: Python :: 3.10
Classifier: Programming Language :: Python :: 3.11
Classifier: Programming Language :: Python :: 3.12
Classifier: Topic :: Scientific/Engineering
Classifier: Topic :: Scientific/Engineering :: Artificial Intelligence
Requires-Python: >=3.10
Requires-Dist: httpx>=0.25.0
Requires-Dist: semantic-kernel>=1.0.0
Provides-Extra: dev
Requires-Dist: pytest-asyncio>=0.21; extra == 'dev'
Requires-Dist: pytest>=7.0; extra == 'dev'
